MANIFEST.in
setup.py
ApiDaemon/__init__.py
ApiDaemon/config_default.yml
ApiDaemon/exceptions.py
ApiDaemon/runner.py
ApiDaemon/server.py
ApiDaemon/version
ApiDaemon.egg-info/PKG-INFO
ApiDaemon.egg-info/SOURCES.txt
ApiDaemon.egg-info/dependency_links.txt
ApiDaemon.egg-info/entry_points.txt
ApiDaemon.egg-info/not-zip-safe
ApiDaemon.egg-info/requires.txt
ApiDaemon.egg-info/top_level.txt
ApiDaemon/decorators/__init__.py
ApiDaemon/decorators/rate_limited.py
ApiDaemon/notificators/__init__.py
ApiDaemon/notificators/email.py
ApiDaemon/plugins/__init__.py
ApiDaemon/plugins/lastfm.py
ApiDaemon/plugins/plugin_example.py
ApiDaemon/plugins/vk.py