Metadata-Version: 1.1
Name: ApiDaemon
Version: 0.3.6.3
Summary: Daemon for wraps any external APIs
Home-page: https://github.com/tsyganov-ivan/ApiDaemon
Author: Ivan Tsyganov
Author-email: tsyganov.ivan@gmail.com
License: MIT-license
Platform: UNKNOWN
Classifier: Natural Language :: English
Classifier: Operating System :: POSIX
Classifier: Programming Language :: Python :: 3.4
